syre_version_converter/__about__.py
syre_version_converter/__init__.py
syre_version_converter/__main__.py
syre_version_converter/common.py
syre_version_converter/convert_0_10_0.py
syre_version_converter/convert_0_10_1.py
syre_version_converter/convert_0_10_2.py
syre_version_converter/convert_0_9_x.py
syre_version_converter/paths.py
syre_version_converter-0.11.1.dist-info/METADATA
syre_version_converter-0.11.1.dist-info/WHEEL
syre_version_converter-0.11.1.dist-info/licenses/LICENSE.txt
syre_version_converter-0.11.1.dist-info/RECORD
