Metadata-Version: 2.4
Name: syre-version-converter
Version: 0.11.1
Project-URL: Documentation, https://github.com/syre-data/version_converter#readme
Project-URL: Issues, https://github.com/syre-data/version_converter/issues
Project-URL: Source, https://github.com/syre-data/version_converter
Author-email: Brian Carlsen <carlsen.bri@gmail.com>
License-Expression: MIT
License-File: LICENSE.txt
Classifier: Development Status :: 4 - Beta
Classifier: Programming Language :: Python
Classifier: Programming Language :: Python :: 3.8
Classifier: Programming Language :: Python :: 3.9
Classifier: Programming Language :: Python :: 3.10
Classifier: Programming Language :: Python :: 3.11
Classifier: Programming Language :: Python :: 3.12
Classifier: Programming Language :: Python :: Implementation :: CPython
Classifier: Programming Language :: Python :: Implementation :: PyPy
Requires-Python: >=3.8
